[
    {
        "name": "flow_id",
        "description": "Unique identifier of the network flow",
        "category": "flow",
        "datatype": "string",
        "unit": "",
        "minimum": null,
        "maximum": null,
        "nullable": false,
        "normalization": "none",
        "source": "flow_extractor",
        "required": true,
        "derived": false,
        "ml_role": "metadata"
    },
    {
        "name": "flow_duration_ms",
        "description": "Total duration of the network flow",
        "category": "flow",
        "datatype": "float",
        "unit": "ms",
        "minimum": 0,
        "maximum": null,
        "nullable": false,
        "normalization": "standard",
        "source": "flow_extractor",
        "required": true,
        "derived": false,
        "ml_role": "feature"
    },
    {
        "name": "packet_count",
        "description": "Total number of packets in the flow",
        "category": "flow",
        "datatype": "int",
        "unit": "packets",
        "minimum": 1,
        "maximum": null,
        "nullable": false,
        "normalization": "log",
        "source": "flow_extractor",
        "required": true,
        "derived": false,
        "ml_role": "feature"
    },
    {
        "name": "byte_count",
        "description": "Total bytes transferred",
        "category": "flow",
        "datatype": "int",
        "unit": "bytes",
        "minimum": 1,
        "maximum": null,
        "nullable": false,
        "normalization": "log",
        "source": "flow_extractor",
        "required": true,
        "derived": false,
        "ml_role": "feature"
    },
    {
        "name": "forward_packet_count",
        "description": "Packets sent from source to destination",
        "category": "flow",
        "datatype": "int",
        "unit": "packets",
        "minimum": 0,
        "maximum": null,
        "nullable": false,
        "normalization": "log",
        "source": "flow_extractor",
        "required": true,
        "derived": false,
        "ml_role": "feature"
    },
    {
        "name": "backward_packet_count",
        "description": "Packets sent from destination to source",
        "category": "flow",
        "datatype": "int",
        "unit": "packets",
        "minimum": 0,
        "maximum": null,
        "nullable": false,
        "normalization": "log",
        "source": "flow_extractor",
        "required": true,
        "derived": false,
        "ml_role": "feature"
    },
    {
        "name": "forward_byte_count",
        "description": "Bytes transferred from source to destination",
        "category": "flow",
        "datatype": "int",
        "unit": "bytes",
        "minimum": 0,
        "maximum": null,
        "nullable": false,
        "normalization": "log",
        "source": "flow_extractor",
        "required": true,
        "derived": false,
        "ml_role": "feature"
    },
    {
        "name": "backward_byte_count",
        "description": "Bytes transferred from destination to source",
        "category": "flow",
        "datatype": "int",
        "unit": "bytes",
        "minimum": 0,
        "maximum": null,
        "nullable": false,
        "normalization": "log",
        "source": "flow_extractor",
        "required": true,
        "derived": false,
        "ml_role": "feature"
    },
    {
        "name": "packet_rate_pps",
        "description": "Packets transmitted per second",
        "category": "flow",
        "datatype": "float",
        "unit": "packets/sec",
        "minimum": 0,
        "maximum": null,
        "nullable": false,
        "normalization": "standard",
        "source": "flow_extractor",
        "required": true,
        "derived": false,
        "ml_role": "feature"
    },
    {
        "name": "byte_rate_bps",
        "description": "Bytes transmitted per second",
        "category": "flow",
        "datatype": "float",
        "unit": "bytes/sec",
        "minimum": 0,
        "maximum": null,
        "nullable": false,
        "normalization": "standard",
        "source": "flow_extractor",
        "required": true,
        "derived": false,
        "ml_role": "feature"
    },
    {
        "name": "flow_start_time",
        "description": "Timestamp when the flow started",
        "category": "flow",
        "datatype": "datetime",
        "unit": "UTC",
        "minimum": null,
        "maximum": null,
        "nullable": false,
        "normalization": "none",
        "source": "flow_extractor",
        "required": true,
        "derived": false,
        "ml_role": "metadata"
    },
    {
        "name": "flow_end_time",
        "description": "Timestamp when the flow ended",
        "category": "flow",
        "datatype": "datetime",
        "unit": "UTC",
        "minimum": null,
        "maximum": null,
        "nullable": false,
        "normalization": "none",
        "source": "flow_extractor",
        "required": true,
        "derived": false,
        "ml_role": "metadata"
    },
    {
        "name": "ether_type",
        "description": "Ethernet frame type",
        "category": "layer2",
        "datatype": "category",
        "unit": "",
        "minimum": null,
        "maximum": null,
        "nullable": false,
        "normalization": "none",
        "source": "packet_parser",
        "required": true,
        "derived": false,
        "ml_role": "feature"
    },
    {
        "name": "vlan_present",
        "description": "Whether the Ethernet frame contains a VLAN tag",
        "category": "layer2",
        "datatype": "bool",
        "unit": "",
        "minimum": null,
        "maximum": null,
        "nullable": false,
        "normalization": "none",
        "source": "packet_parser",
        "required": true,
        "derived": false,
        "ml_role": "feature"
    },
    {
        "name": "vlan_priority",
        "description": "IEEE 802.1p VLAN priority value",
        "category": "layer2",
        "datatype": "int",
        "unit": "priority",
        "minimum": 0,
        "maximum": 7,
        "nullable": false,
        "normalization": "none",
        "source": "packet_parser",
        "required": true,
        "derived": false,
        "ml_role": "feature"
    },
    {
        "name": "broadcast_frame",
        "description": "Whether the frame is broadcast",
        "category": "layer2",
        "datatype": "bool",
        "unit": "",
        "minimum": null,
        "maximum": null,
        "nullable": false,
        "normalization": "none",
        "source": "packet_parser",
        "required": true,
        "derived": false,
        "ml_role": "feature"
    },
    {
        "name": "multicast_frame",
        "description": "Whether the frame is multicast",
        "category": "layer2",
        "datatype": "bool",
        "unit": "",
        "minimum": null,
        "maximum": null,
        "nullable": false,
        "normalization": "none",
        "source": "packet_parser",
        "required": true,
        "derived": false,
        "ml_role": "feature"
    },
    {
        "name": "ip_version",
        "description": "Internet Protocol version",
        "category": "layer3",
        "datatype": "category",
        "unit": "",
        "minimum": null,
        "maximum": null,
        "nullable": false,
        "normalization": "none",
        "source": "packet_parser",
        "required": true,
        "derived": false,
        "ml_role": "feature"
    },
    {
        "name": "ttl",
        "description": "IPv4 Time-To-Live or IPv6 Hop Limit",
        "category": "layer3",
        "datatype": "int",
        "unit": "hops",
        "minimum": 0,
        "maximum": 255,
        "nullable": false,
        "normalization": "none",
        "source": "packet_parser",
        "required": true,
        "derived": false,
        "ml_role": "feature"
    },
    {
        "name": "dscp",
        "description": "Differentiated Services Code Point",
        "category": "layer3",
        "datatype": "int",
        "unit": "",
        "minimum": 0,
        "maximum": 63,
        "nullable": false,
        "normalization": "none",
        "source": "packet_parser",
        "required": true,
        "derived": false,
        "ml_role": "feature"
    },
    {
        "name": "ecn",
        "description": "Explicit Congestion Notification value",
        "category": "layer3",
        "datatype": "int",
        "unit": "",
        "minimum": 0,
        "maximum": 3,
        "nullable": false,
        "normalization": "none",
        "source": "packet_parser",
        "required": true,
        "derived": false,
        "ml_role": "feature"
    },
    {
        "name": "ip_packet_length",
        "description": "Total IP packet length",
        "category": "layer3",
        "datatype": "int",
        "unit": "bytes",
        "minimum": 0,
        "maximum": null,
        "nullable": false,
        "normalization": "log",
        "source": "packet_parser",
        "required": true,
        "derived": false,
        "ml_role": "feature"
    },
    {
        "name": "fragmented",
        "description": "Whether the packet is fragmented",
        "category": "layer3",
        "datatype": "bool",
        "unit": "",
        "minimum": null,
        "maximum": null,
        "nullable": false,
        "normalization": "none",
        "source": "packet_parser",
        "required": true,
        "derived": false,
        "ml_role": "feature"
    },
    {
        "name": "ip_header_length",
        "description": "Length of the IP header",
        "category": "layer3",
        "datatype": "int",
        "unit": "bytes",
        "minimum": 20,
        "maximum": null,
        "nullable": false,
        "normalization": "none",
        "source": "packet_parser",
        "required": true,
        "derived": false,
        "ml_role": "feature"
    },
    {
        "name": "hop_limit",
        "description": "IPv6 Hop Limit (mirrors TTL for IPv6)",
        "category": "layer3",
        "datatype": "int",
        "unit": "hops",
        "minimum": 0,
        "maximum": 255,
        "nullable": false,
        "normalization": "none",
        "source": "packet_parser",
        "required": true,
        "derived": false,
        "ml_role": "feature"
    },
    {
        "name": "transport_protocol",
        "description": "Transport layer protocol used by the flow",
        "category": "layer4",
        "datatype": "string",
        "unit": "",
        "minimum": null,
        "maximum": null,
        "nullable": false,
        "normalization": "none",
        "source": "packet_parser",
        "required": true,
        "derived": false,
        "ml_role": "feature"
    },
    {
        "name": "source_port",
        "description": "Source transport layer port",
        "category": "layer4",
        "datatype": "int",
        "unit": "",
        "minimum": 0,
        "maximum": 65535,
        "nullable": false,
        "normalization": "none",
        "source": "packet_parser",
        "required": true,
        "derived": false,
        "ml_role": "feature"
    },
    {
        "name": "destination_port",
        "description": "Destination transport layer port",
        "category": "layer4",
        "datatype": "int",
        "unit": "",
        "minimum": 0,
        "maximum": 65535,
        "nullable": false,
        "normalization": "none",
        "source": "packet_parser",
        "required": true,
        "derived": false,
        "ml_role": "feature"
    },
    {
        "name": "tcp_syn_count",
        "description": "Number of TCP SYN packets",
        "category": "layer4",
        "datatype": "int",
        "unit": "packets",
        "minimum": 0,
        "maximum": null,
        "nullable": false,
        "normalization": "log",
        "source": "packet_parser",
        "required": true,
        "derived": false,
        "ml_role": "feature"
    },
    {
        "name": "tcp_ack_count",
        "description": "Number of TCP ACK packets",
        "category": "layer4",
        "datatype": "int",
        "unit": "packets",
        "minimum": 0,
        "maximum": null,
        "nullable": false,
        "normalization": "log",
        "source": "packet_parser",
        "required": true,
        "derived": false,
        "ml_role": "feature"
    },
    {
        "name": "tcp_fin_count",
        "description": "Number of TCP FIN packets",
        "category": "layer4",
        "datatype": "int",
        "unit": "packets",
        "minimum": 0,
        "maximum": null,
        "nullable": false,
        "normalization": "log",
        "source": "packet_parser",
        "required": true,
        "derived": false,
        "ml_role": "feature"
    },
    {
        "name": "tcp_rst_count",
        "description": "Number of TCP RST packets",
        "category": "layer4",
        "datatype": "int",
        "unit": "packets",
        "minimum": 0,
        "maximum": null,
        "nullable": false,
        "normalization": "log",
        "source": "packet_parser",
        "required": true,
        "derived": false,
        "ml_role": "feature"
    },
    {
        "name": "tcp_window_size",
        "description": "Average TCP receive window size",
        "category": "layer4",
        "datatype": "int",
        "unit": "bytes",
        "minimum": 0,
        "maximum": null,
        "nullable": false,
        "normalization": "standard",
        "source": "packet_parser",
        "required": true,
        "derived": false,
        "ml_role": "feature"
    },
    {
        "name": "tcp_retransmissions",
        "description": "Number of retransmitted TCP packets",
        "category": "layer4",
        "datatype": "int",
        "unit": "packets",
        "minimum": 0,
        "maximum": null,
        "nullable": false,
        "normalization": "log",
        "source": "packet_parser",
        "required": true,
        "derived": false,
        "ml_role": "feature"
    },
    {
        "name": "udp_packet_count",
        "description": "Number of UDP packets",
        "category": "layer4",
        "datatype": "int",
        "unit": "packets",
        "minimum": 0,
        "maximum": null,
        "nullable": false,
        "normalization": "log",
        "source": "packet_parser",
        "required": true,
        "derived": false,
        "ml_role": "feature"
    },
    {
        "name": "mean_iat_ms",
        "description": "Mean inter-arrival time between packets",
        "category": "temporal",
        "datatype": "float",
        "unit": "ms",
        "minimum": 0,
        "maximum": null,
        "nullable": false,
        "normalization": "standard",
        "source": "flow_extractor",
        "required": true,
        "derived": false,
        "ml_role": "feature"
    },
    {
        "name": "std_iat_ms",
        "description": "Standard deviation of packet inter-arrival time",
        "category": "temporal",
        "datatype": "float",
        "unit": "ms",
        "minimum": 0,
        "maximum": null,
        "nullable": false,
        "normalization": "standard",
        "source": "flow_extractor",
        "required": true,
        "derived": false,
        "ml_role": "feature"
    },
    {
        "name": "min_iat_ms",
        "description": "Minimum packet inter-arrival time",
        "category": "temporal",
        "datatype": "float",
        "unit": "ms",
        "minimum": 0,
        "maximum": null,
        "nullable": false,
        "normalization": "standard",
        "source": "flow_extractor",
        "required": true,
        "derived": false,
        "ml_role": "feature"
    },
    {
        "name": "max_iat_ms",
        "description": "Maximum packet inter-arrival time",
        "category": "temporal",
        "datatype": "float",
        "unit": "ms",
        "minimum": 0,
        "maximum": null,
        "nullable": false,
        "normalization": "standard",
        "source": "flow_extractor",
        "required": true,
        "derived": false,
        "ml_role": "feature"
    },
    {
        "name": "forward_mean_iat_ms",
        "description": "Mean forward-direction inter-arrival time",
        "category": "temporal",
        "datatype": "float",
        "unit": "ms",
        "minimum": 0,
        "maximum": null,
        "nullable": false,
        "normalization": "standard",
        "source": "flow_extractor",
        "required": true,
        "derived": false,
        "ml_role": "feature"
    },
    {
        "name": "backward_mean_iat_ms",
        "description": "Mean backward-direction inter-arrival time",
        "category": "temporal",
        "datatype": "float",
        "unit": "ms",
        "minimum": 0,
        "maximum": null,
        "nullable": false,
        "normalization": "standard",
        "source": "flow_extractor",
        "required": true,
        "derived": false,
        "ml_role": "feature"
    },
    {
        "name": "flow_active_time_ms",
        "description": "Total active transmission time",
        "category": "temporal",
        "datatype": "float",
        "unit": "ms",
        "minimum": 0,
        "maximum": null,
        "nullable": false,
        "normalization": "standard",
        "source": "flow_extractor",
        "required": true,
        "derived": false,
        "ml_role": "feature"
    },
    {
        "name": "flow_idle_time_ms",
        "description": "Total idle time during the flow",
        "category": "temporal",
        "datatype": "float",
        "unit": "ms",
        "minimum": 0,
        "maximum": null,
        "nullable": false,
        "normalization": "standard",
        "source": "flow_extractor",
        "required": true,
        "derived": false,
        "ml_role": "feature"
    },
    {
        "name": "mean_packet_size",
        "description": "Average packet size within the flow",
        "category": "statistical",
        "datatype": "float",
        "unit": "bytes",
        "minimum": 0,
        "maximum": null,
        "nullable": false,
        "normalization": "standard",
        "source": "flow_extractor",
        "required": true,
        "derived": false,
        "ml_role": "feature"
    },
    {
        "name": "median_packet_size",
        "description": "Median packet size within the flow",
        "category": "statistical",
        "datatype": "float",
        "unit": "bytes",
        "minimum": 0,
        "maximum": null,
        "nullable": false,
        "normalization": "standard",
        "source": "flow_extractor",
        "required": true,
        "derived": false,
        "ml_role": "feature"
    },
    {
        "name": "min_packet_size",
        "description": "Minimum packet size observed in the flow",
        "category": "statistical",
        "datatype": "int",
        "unit": "bytes",
        "minimum": 0,
        "maximum": null,
        "nullable": false,
        "normalization": "none",
        "source": "flow_extractor",
        "required": true,
        "derived": false,
        "ml_role": "feature"
    },
    {
        "name": "max_packet_size",
        "description": "Maximum packet size observed in the flow",
        "category": "statistical",
        "datatype": "int",
        "unit": "bytes",
        "minimum": 0,
        "maximum": null,
        "nullable": false,
        "normalization": "none",
        "source": "flow_extractor",
        "required": true,
        "derived": false,
        "ml_role": "feature"
    },
    {
        "name": "std_packet_size",
        "description": "Standard deviation of packet sizes",
        "category": "statistical",
        "datatype": "float",
        "unit": "bytes",
        "minimum": 0,
        "maximum": null,
        "nullable": false,
        "normalization": "standard",
        "source": "flow_extractor",
        "required": true,
        "derived": false,
        "ml_role": "feature"
    },
    {
        "name": "variance_packet_size",
        "description": "Variance of packet sizes",
        "category": "statistical",
        "datatype": "float",
        "unit": "bytes\u00b2",
        "minimum": 0,
        "maximum": null,
        "nullable": false,
        "normalization": "standard",
        "source": "flow_extractor",
        "required": true,
        "derived": false,
        "ml_role": "feature"
    },
    {
        "name": "packet_size_range",
        "description": "Difference between maximum and minimum packet sizes",
        "category": "statistical",
        "datatype": "int",
        "unit": "bytes",
        "minimum": 0,
        "maximum": null,
        "nullable": false,
        "normalization": "none",
        "source": "flow_extractor",
        "required": true,
        "derived": false,
        "ml_role": "feature"
    },
    {
        "name": "packet_size_skewness",
        "description": "Skewness of packet size distribution",
        "category": "statistical",
        "datatype": "float",
        "unit": "",
        "minimum": null,
        "maximum": null,
        "nullable": false,
        "normalization": "standard",
        "source": "flow_extractor",
        "required": true,
        "derived": true,
        "ml_role": "feature"
    },
    {
        "name": "packet_size_kurtosis",
        "description": "Kurtosis of packet size distribution",
        "category": "statistical",
        "datatype": "float",
        "unit": "",
        "minimum": null,
        "maximum": null,
        "nullable": false,
        "normalization": "standard",
        "source": "flow_extractor",
        "required": true,
        "derived": true,
        "ml_role": "feature"
    },
    {
        "name": "coefficient_of_variation_packet_size",
        "description": "Coefficient of variation of packet sizes",
        "category": "statistical",
        "datatype": "float",
        "unit": "",
        "minimum": 0,
        "maximum": null,
        "nullable": false,
        "normalization": "standard",
        "source": "flow_extractor",
        "required": true,
        "derived": true,
        "ml_role": "feature"
    },
    {
        "name": "end_to_end_latency_ms",
        "description": "Average end-to-end latency experienced by the flow",
        "category": "qos",
        "datatype": "float",
        "unit": "ms",
        "minimum": 0,
        "maximum": null,
        "nullable": false,
        "normalization": "standard",
        "source": "qos_estimator",
        "required": true,
        "derived": false,
        "ml_role": "feature"
    },
    {
        "name": "jitter_ms",
        "description": "Variation in packet arrival time",
        "category": "qos",
        "datatype": "float",
        "unit": "ms",
        "minimum": 0,
        "maximum": null,
        "nullable": false,
        "normalization": "standard",
        "source": "qos_estimator",
        "required": true,
        "derived": false,
        "ml_role": "feature"
    },
    {
        "name": "packet_loss_rate",
        "description": "Percentage of packets lost during transmission",
        "category": "qos",
        "datatype": "float",
        "unit": "%",
        "minimum": 0,
        "maximum": 100,
        "nullable": false,
        "normalization": "minmax",
        "source": "qos_estimator",
        "required": true,
        "derived": false,
        "ml_role": "feature"
    },
    {
        "name": "throughput_mbps",
        "description": "Average throughput achieved by the flow",
        "category": "qos",
        "datatype": "float",
        "unit": "Mbps",
        "minimum": 0,
        "maximum": null,
        "nullable": false,
        "normalization": "standard",
        "source": "qos_estimator",
        "required": true,
        "derived": false,
        "ml_role": "feature"
    },
    {
        "name": "goodput_mbps",
        "description": "Application-level useful throughput excluding retransmissions",
        "category": "qos",
        "datatype": "float",
        "unit": "Mbps",
        "minimum": 0,
        "maximum": null,
        "nullable": false,
        "normalization": "standard",
        "source": "qos_estimator",
        "required": true,
        "derived": true,
        "ml_role": "feature"
    },
    {
        "name": "bandwidth_utilization_pct",
        "description": "Percentage of allocated bandwidth utilized",
        "category": "qos",
        "datatype": "float",
        "unit": "%",
        "minimum": 0,
        "maximum": 100,
        "nullable": false,
        "normalization": "minmax",
        "source": "qos_estimator",
        "required": true,
        "derived": true,
        "ml_role": "feature"
    },
    {
        "name": "queueing_delay_ms",
        "description": "Average queueing delay experienced by packets",
        "category": "qos",
        "datatype": "float",
        "unit": "ms",
        "minimum": 0,
        "maximum": null,
        "nullable": false,
        "normalization": "standard",
        "source": "qos_estimator",
        "required": true,
        "derived": true,
        "ml_role": "feature"
    },
    {
        "name": "retransmission_rate",
        "description": "Percentage of retransmitted packets",
        "category": "qos",
        "datatype": "float",
        "unit": "%",
        "minimum": 0,
        "maximum": 100,
        "nullable": false,
        "normalization": "minmax",
        "source": "qos_estimator",
        "required": true,
        "derived": true,
        "ml_role": "feature"
    },
    {
        "name": "link_utilization_pct",
        "description": "Percentage utilization of the serving link",
        "category": "qos",
        "datatype": "float",
        "unit": "%",
        "minimum": 0,
        "maximum": 100,
        "nullable": false,
        "normalization": "minmax",
        "source": "qos_estimator",
        "required": true,
        "derived": true,
        "ml_role": "feature"
    },
    {
        "name": "qos_satisfaction_score",
        "description": "Composite QoS score derived from latency, jitter, packet loss and throughput",
        "category": "qos",
        "datatype": "float",
        "unit": "score",
        "minimum": 0,
        "maximum": 1,
        "nullable": false,
        "normalization": "none",
        "source": "qos_estimator",
        "required": true,
        "derived": true,
        "ml_role": "feature"
    },
    {
        "name": "service_type",
        "description": "High-level service category",
        "category": "context",
        "datatype": "category",
        "unit": "",
        "minimum": null,
        "maximum": null,
        "nullable": false,
        "normalization": "none",
        "source": "context_injector",
        "required": true,
        "derived": false,
        "ml_role": "feature"
    },
    {
        "name": "application_name",
        "description": "Application generating the traffic",
        "category": "context",
        "datatype": "string",
        "unit": "",
        "minimum": null,
        "maximum": null,
        "nullable": false,
        "normalization": "none",
        "source": "context_injector",
        "required": true,
        "derived": false,
        "ml_role": "feature"
    },
    {
        "name": "slice_type",
        "description": "Target network slice type",
        "category": "context",
        "datatype": "category",
        "unit": "",
        "minimum": null,
        "maximum": null,
        "nullable": false,
        "normalization": "none",
        "source": "context_injector",
        "required": true,
        "derived": false,
        "ml_role": "feature"
    },
    {
        "name": "service_priority",
        "description": "Priority assigned to the service",
        "category": "context",
        "datatype": "int",
        "unit": "level",
        "minimum": 1,
        "maximum": 4,
        "nullable": false,
        "normalization": "none",
        "source": "context_injector",
        "required": true,
        "derived": false,
        "ml_role": "feature"
    },
    {
        "name": "network_load_pct",
        "description": "Overall network utilization",
        "category": "context",
        "datatype": "float",
        "unit": "%",
        "minimum": 0,
        "maximum": 100,
        "nullable": false,
        "normalization": "minmax",
        "source": "context_injector",
        "required": true,
        "derived": false,
        "ml_role": "feature"
    },
    {
        "name": "cell_load_pct",
        "description": "Serving cell utilization",
        "category": "context",
        "datatype": "float",
        "unit": "%",
        "minimum": 0,
        "maximum": 100,
        "nullable": false,
        "normalization": "minmax",
        "source": "context_injector",
        "required": true,
        "derived": false,
        "ml_role": "feature"
    },
    {
        "name": "active_users",
        "description": "Number of active users in the serving cell",
        "category": "context",
        "datatype": "int",
        "unit": "users",
        "minimum": 0,
        "maximum": null,
        "nullable": false,
        "normalization": "log",
        "source": "context_injector",
        "required": true,
        "derived": false,
        "ml_role": "feature"
    },
    {
        "name": "device_type",
        "description": "Type of user equipment",
        "category": "context",
        "datatype": "category",
        "unit": "",
        "minimum": null,
        "maximum": null,
        "nullable": false,
        "normalization": "none",
        "source": "context_injector",
        "required": true,
        "derived": false,
        "ml_role": "feature"
    },
    {
        "name": "mobility_state",
        "description": "Mobility state of the user",
        "category": "context",
        "datatype": "category",
        "unit": "",
        "minimum": null,
        "maximum": null,
        "nullable": false,
        "normalization": "none",
        "source": "context_injector",
        "required": true,
        "derived": false,
        "ml_role": "feature"
    },
    {
        "name": "time_of_day",
        "description": "Time period when the flow was generated",
        "category": "context",
        "datatype": "category",
        "unit": "",
        "minimum": null,
        "maximum": null,
        "nullable": false,
        "normalization": "none",
        "source": "context_injector",
        "required": true,
        "derived": false,
        "ml_role": "feature"
    },
    {
        "name": "signal_strength_dbm",
        "description": "Average received signal strength",
        "category": "context",
        "datatype": "float",
        "unit": "dBm",
        "minimum": null,
        "maximum": null,
        "nullable": false,
        "normalization": "standard",
        "source": "context_injector",
        "required": true,
        "derived": false,
        "ml_role": "feature"
    },
    {
        "name": "sinr_db",
        "description": "Signal-to-Interference-plus-Noise Ratio",
        "category": "context",
        "datatype": "float",
        "unit": "dB",
        "minimum": null,
        "maximum": null,
        "nullable": false,
        "normalization": "standard",
        "source": "context_injector",
        "required": true,
        "derived": false,
        "ml_role": "feature"
    },
    {
        "name": "rsrp_dbm",
        "description": "Reference Signal Received Power",
        "category": "context",
        "datatype": "float",
        "unit": "dBm",
        "minimum": null,
        "maximum": null,
        "nullable": false,
        "normalization": "standard",
        "source": "context_injector",
        "required": true,
        "derived": false,
        "ml_role": "feature"
    },
    {
        "name": "rsrq_db",
        "description": "Reference Signal Received Quality",
        "category": "context",
        "datatype": "float",
        "unit": "dB",
        "minimum": null,
        "maximum": null,
        "nullable": false,
        "normalization": "standard",
        "source": "context_injector",
        "required": true,
        "derived": false,
        "ml_role": "feature"
    },
    {
        "name": "cqi",
        "description": "Channel Quality Indicator",
        "category": "context",
        "datatype": "int",
        "unit": "index",
        "minimum": 1,
        "maximum": 15,
        "nullable": false,
        "normalization": "none",
        "source": "context_injector",
        "required": true,
        "derived": false,
        "ml_role": "feature"
    },
    {
        "name": "network_slice_id",
        "description": "Identifier of the serving network slice",
        "category": "context",
        "datatype": "category",
        "unit": "",
        "minimum": null,
        "maximum": null,
        "nullable": false,
        "normalization": "none",
        "source": "context_injector",
        "required": true,
        "derived": false,
        "ml_role": "feature"
    },
    {
        "name": "slice_resource_utilization_pct",
        "description": "Percentage of slice resources currently utilized",
        "category": "context",
        "datatype": "float",
        "unit": "%",
        "minimum": 0,
        "maximum": 100,
        "nullable": false,
        "normalization": "minmax",
        "source": "context_injector",
        "required": true,
        "derived": false,
        "ml_role": "feature"
    },
    {
        "name": "radio_resource_blocks_used",
        "description": "Allocated Physical Resource Blocks",
        "category": "context",
        "datatype": "int",
        "unit": "PRBs",
        "minimum": 0,
        "maximum": null,
        "nullable": false,
        "normalization": "log",
        "source": "context_injector",
        "required": true,
        "derived": false,
        "ml_role": "feature"
    },
    {
        "name": "handover_in_progress",
        "description": "Whether the UE is undergoing handover",
        "category": "context",
        "datatype": "bool",
        "unit": "",
        "minimum": null,
        "maximum": null,
        "nullable": false,
        "normalization": "none",
        "source": "context_injector",
        "required": true,
        "derived": false,
        "ml_role": "feature"
    },
    {
        "name": "service_class",
        "description": "Ground truth service class",
        "category": "label",
        "datatype": "category",
        "unit": "",
        "minimum": null,
        "maximum": null,
        "nullable": false,
        "normalization": "none",
        "source": "labeler",
        "required": true,
        "derived": false,
        "ml_role": "label"
    },
    {
        "name": "application_id",
        "description": "Application responsible for generating the flow",
        "category": "label",
        "datatype": "category",
        "unit": "",
        "minimum": null,
        "maximum": null,
        "nullable": false,
        "normalization": "none",
        "source": "labeler",
        "required": true,
        "derived": false,
        "ml_role": "label"
    },
    {
        "name": "slice_type_label",
        "description": "Ground truth slice type",
        "category": "label",
        "datatype": "category",
        "unit": "",
        "minimum": null,
        "maximum": null,
        "nullable": false,
        "normalization": "none",
        "source": "labeler",
        "required": true,
        "derived": false,
        "ml_role": "label"
    },
    {
        "name": "priority_level",
        "description": "Ground truth service priority",
        "category": "label",
        "datatype": "int",
        "unit": "level",
        "minimum": 1,
        "maximum": 4,
        "nullable": false,
        "normalization": "none",
        "source": "labeler",
        "required": true,
        "derived": false,
        "ml_role": "label"
    },
    {
        "name": "allocated_slice",
        "description": "Slice allocated by the scheduling policy",
        "category": "label",
        "datatype": "category",
        "unit": "",
        "minimum": null,
        "maximum": null,
        "nullable": false,
        "normalization": "none",
        "source": "labeler",
        "required": true,
        "derived": true,
        "ml_role": "label"
    },
    {
        "name": "sla_satisfied",
        "description": "Whether the flow met its SLA requirements",
        "category": "label",
        "datatype": "bool",
        "unit": "",
        "minimum": null,
        "maximum": null,
        "nullable": false,
        "normalization": "none",
        "source": "labeler",
        "required": true,
        "derived": true,
        "ml_role": "label"
    },
    {
        "name": "reward_score",
        "description": "Reward assigned to the scheduling decision",
        "category": "label",
        "datatype": "float",
        "unit": "score",
        "minimum": null,
        "maximum": null,
        "nullable": false,
        "normalization": "none",
        "source": "labeler",
        "required": true,
        "derived": true,
        "ml_role": "label"
    }
]